aigeodb/__init__.py
aigeodb/core/__init__.py
aigeodb/core/analytics.py
aigeodb/core/database.py
aigeodb/core/db_models.py
aigeodb/core/downloader.py
aigeodb/core/py_models.py
aigeodb/django/__init__.py
aigeodb/django/admin.py
aigeodb/django/apps.py
aigeodb/django/urls.py
aigeodb/django/views.py
aigeodb/django/fields/__init__.py
aigeodb/django/fields/city.py
aigeodb/django/fields/country.py
aigeodb/django/fields/widgets.py
aigeodb/django/static/.DS_Store
aigeodb/django/static/aigeodb/css/autocomplete-theme.css
aigeodb/django/static/aigeodb/js/autocomplete-init.js
aigeodb/sqlite/cities.sqlite3
aigeodb/sqlite/countries.sqlite3
aigeodb/sqlite/regions.sqlite3
aigeodb/sqlite/states.sqlite3
aigeodb/sqlite/subregions.sqlite3
aigeodb/sqlite/world.sqlite3
aigeodb-0.2.6.dist-info/LICENSE
aigeodb-0.2.6.dist-info/METADATA
aigeodb-0.2.6.dist-info/WHEEL
aigeodb-0.2.6.dist-info/top_level.txt
aigeodb-0.2.6.dist-info/RECORD
