Metadata-Version: 2.2
Name: aigeodb
Version: 0.2.6
Summary: Comprehensive Python package for managing world geographical data with SQLite backend, Django integration, and advanced geolocation features. Includes 150K+ cities, countries, regions with search, distance calculation, and Select2-powered autocomplete widgets.
Home-page: https://github.com/markolofsen/aigeodb
Author: Unrealos
Author-email: info@unrealos.com
License: MIT
Project-URL: Source, https://github.com/markolofsen/aigeodb
Project-URL: Tracker, https://github.com/markolofsen/aigeodb/issues
Project-URL: Documentation, https://github.com/markolofsen/aigeodb#readme
Classifier: Development Status :: 4 - Beta
Classifier: Intended Audience :: Developers
Classifier: Intended Audience :: Information Technology
Classifier: Intended Audience :: Science/Research
Classifier: Topic :: Software Development :: Libraries
Classifier: Topic :: Scientific/Engineering :: GIS
Classifier: Topic :: Database
Classifier: Framework :: Django
Classifier: Programming Language :: Python :: 3.7
Classifier: Programming Language :: Python :: 3.8
Classifier: Programming Language :: Python :: 3.9
Classifier: Programming Language :: Python :: 3.10
Classifier: Programming Language :: Python :: 3.11
Classifier: License :: OSI Approved :: MIT License
Classifier: Operating System :: OS Independent
Requires-Python: >=3.7
License-File: LICENSE
Requires-Dist: geopy>=2.3.0
Requires-Dist: peewee>=3.16.0
Requires-Dist: requests>=2.28.0
Requires-Dist: pydantic>=2.0.0
Provides-Extra: django
Requires-Dist: Django>=3.2; extra == "django"
Provides-Extra: dev
Requires-Dist: pytest>=7.0.0; extra == "dev"
Requires-Dist: pytest-cov>=4.0.0; extra == "dev"
Requires-Dist: black>=23.0.0; extra == "dev"
Requires-Dist: flake8>=6.0.0; extra == "dev"
Requires-Dist: isort>=5.12.0; extra == "dev"
Requires-Dist: build>=0.10.0; extra == "dev"
Requires-Dist: twine>=4.0.0; extra == "dev"
Requires-Dist: python-dotenv>=1.0.0; extra == "dev"
